uwsgiwebtop
