Metadata-Version: 1.1
Name: uwsgiwebtop
Version: 0.2
Summary: Web application to aggregate stats from multiple uWSGI instances
Home-page: https://github.com/skruger/uwsgiwebtop
Author: Shaun Kruger
Author-email: shaun.kruger@gmail.com
License: BSD
Platform: UNKNOWN
Classifier: Development Status :: 3 - Alpha
Classifier: Topic :: Utilities
Classifier: License :: OSI Approved :: BSD License
